[
  {
    "public_info":{
      "surname":"Panço",
      "name":"Hélio",
      "age":27
    },
    "private_info":{
      "balance":431.23,
      "pass":"heliop123"
    }
  },
  {
    "public_info":{
      "surname":"de Souza",
      "name":"Larissa",
      "age":19
    },
    "private_info":{
      "balance":573.9,
      "pass":"laris213"
    }
  },
  {
    "public_info":{
      "surname":"Martins",
      "name":"Giovanni",
      "age":18
    },
    "private_info":{
      "balance":0.66,
      "pass":"gio123"
    }
  },
  {
    "public_info":{
      "surname":"Théo",
      "name":"Jorge",
      "age":45
    },
    "private_info":{
      "balance":100.0,
      "pass":"jorge123"
    }
  },
  {
    "public_info":{
      "surname":"Thimoteo",
      "name":"Flávio",
      "age":"25"
    },
    "private_info":{
      "balance":321.5,
      "pass":"flaviothi123"
    }
  },
  {
    "public_info":{
      "surname":"Machado",
      "name":"Cleber",
      "age":"54"
    },
    "private_info":{
      "balance":82.22,
      "pass":"cl23"
    }
  },
  {
    "public_info":{
      "surname":"Moura",
      "name":"Machado",
      "age":"87"
    },
    "private_info":{
      "balance":58.98,
      "pass":"moura48"
    }
  },
  {
    "public_info":{
      "surname":"Barreto",
      "name":"Raquel",
      "age":"22"
    },
    "private_info":{
      "balance":2.0,
      "pass":"raq123"
    }
  },
  {
    "public_info":{
      "surname":"Assis",
      "name":"Gabriel",
      "age":"21"
    },
    "private_info":{
      "balance":10.0,
      "pass":"assis21"
    }
  }
]